ExpressjsDoc/README.md
ExpressjsDoc/__init__.py
ExpressjsDoc/__main__.py
ExpressjsDoc/file.epub
ExpressjsDoc/index.html
ExpressjsDoc/css/__init__.py
ExpressjsDoc/css/annotations.css
ExpressjsDoc/css/main.css
ExpressjsDoc/css/normalize.css
ExpressjsDoc/css/popup.css
ExpressjsDoc/font/__init__.py
ExpressjsDoc/font/fontello.eot
ExpressjsDoc/font/fontello.svg
ExpressjsDoc/font/fontello.ttf
ExpressjsDoc/font/fontello.woff
ExpressjsDoc/img/__init__.py
ExpressjsDoc/img/annotator-glyph-sprite.png
ExpressjsDoc/img/annotator-icon-sprite.png
ExpressjsDoc/img/apple-touch-icon.png
ExpressjsDoc/img/cancelfullscreen.png
ExpressjsDoc/img/close.png
ExpressjsDoc/img/fullscreen.png
ExpressjsDoc/img/loader.gif
ExpressjsDoc/img/menu-icon.png
ExpressjsDoc/img/save.png
ExpressjsDoc/img/saved.png
ExpressjsDoc/img/settings-s.png
ExpressjsDoc/img/settings.png
ExpressjsDoc/img/star.png
ExpressjsDoc/js/__init__.py
ExpressjsDoc/js/epub.js
ExpressjsDoc/js/epub.min.js
ExpressjsDoc/js/epub.min.map
ExpressjsDoc/js/hooks.min.js
ExpressjsDoc/js/hooks.min.map
ExpressjsDoc/js/reader.js
ExpressjsDoc/js/reader.js.map
ExpressjsDoc/js/reader.min.js
ExpressjsDoc/js/reader.min.map
ExpressjsDoc/js/hooks/__init__.py
ExpressjsDoc/js/hooks/extensions/__init__.py
ExpressjsDoc/js/hooks/extensions/highlight.js
ExpressjsDoc/js/libs/__init__.py
ExpressjsDoc/js/libs/jquery.min.js
ExpressjsDoc/js/libs/localforage.min.js
ExpressjsDoc/js/libs/screenfull.js
ExpressjsDoc/js/libs/screenfull.min.js
ExpressjsDoc/js/libs/zip.min.js
ExpressjsDoc/js/plugins/__init__.py
ExpressjsDoc/js/plugins/hypothesis.js
ExpressjsDoc/js/plugins/search.js
expressjs_doc-2024.3.1.0.dist-info/METADATA
expressjs_doc-2024.3.1.0.dist-info/WHEEL
expressjs_doc-2024.3.1.0.dist-info/entry_points.txt
expressjs_doc-2024.3.1.0.dist-info/top_level.txt
expressjs_doc-2024.3.1.0.dist-info/RECORD
